newspy/__init__.py
newspy/client.py
newspy/models.py
newspy/newsorg/__init__.py
newspy/newsorg/client.py
newspy/newsorg/models.py
newspy/rss/__init__.py
newspy/rss/client.py
newspy/rss/models.py
newspy/shared/__init__.py
newspy/shared/exceptions.py
newspy/shared/http_client.py
newspy/shared/utils.py
newspy/shared/xml_parser.py
newspy-2.2.18.dist-info/METADATA
newspy-2.2.18.dist-info/WHEEL
newspy-2.2.18.dist-info/licenses/LICENSE
newspy-2.2.18.dist-info/RECORD
