Metadata-Version: 2.4
Name: newspy
Version: 2.2.18
Summary: The news client written in Python that fetches and curates the world news across the web.
License: MIT
License-File: LICENSE
Author: Sechaba Mofokeng
Author-email: sechaba@onemoola.com
Requires-Python: >=3.10,<3.15
Classifier: License :: OSI Approved :: MIT License
Classifier: Programming Language :: Python :: 3
Classifier: Programming Language :: Python :: 3.10
Classifier: Programming Language :: Python :: 3.11
Classifier: Programming Language :: Python :: 3.12
Classifier: Programming Language :: Python :: 3.13
Classifier: Programming Language :: Python :: 3.14
Classifier: Programming Language :: Python :: Implementation :: CPython
Requires-Dist: requests (==2.32.5)
Project-URL: Bug Tracker, https://github.com/onemoola/newspy/issues
Project-URL: Documentation, https://github.com/onemoola/newspy#readme
Project-URL: Homepage, https://github.com/onemoola/newspy
Project-URL: Repository, https://github.com/onemoola/newspy
